{
  "version": "2026.07.14",
  "updated": "2026-07-14",
  "note": "Base de assinaturas atualizavel do Telador. Atualize via: telador.exe --update-sigs. Adicionar executor novo = um commit aqui, sem rebuildar o .exe. Severidades validas: high, medium, low.",
  "executor_keywords": {
    "solara": "high",
    "solara executor": "high",
    "xeno executor": "high",
    "wave executor": "high",
    "velocity executor": "high",
    "ronix": "high",
    "ronix executor": "high",
    "krnl": "high",
    "fluxus": "high",
    "synapse x": "high",
    "swift executor": "high",
    "codex executor": "high",
    "delta executor": "high",
    "arceus x": "high",
    "winter bypass": "high",
    "winter executor": "high",
    "fishstrap": "high",
    "cryptic executor": "high",
    "trigon evo": "high",
    "trigon executor": "high",
    "nezur": "high",
    "hydrogen executor": "high",
    "argon executor": "high",
    "electron executor": "high",
    "sentinel executor": "high",
    "moon executor": "high",
    "layuh": "high",
    "nord external": "high",
    "autopsy": "high",
    "lecture external": "high",
    "nocturnal": "high",
    "bauix": "high"
  },
  "executor_process_names": {
    "solara.exe": "high",
    "xeno.exe": "high",
    "wave.exe": "high",
    "velocity.exe": "high",
    "ronix.exe": "high",
    "ronix-bootstrapper.exe": "high",
    "krnl.exe": "high",
    "fluxus.exe": "high",
    "winter.exe": "high",
    "winterbypass.exe": "high",
    "fishstrap.exe": "high",
    "cryptic.exe": "high",
    "trigon.exe": "high",
    "nezur.exe": "high",
    "hydrogen.exe": "high",
    "argon.exe": "high",
    "sentinel.exe": "high",
    "moon.exe": "high",
    "layuh.exe": "high",
    "autopsy.exe": "high",
    "nocturnal.exe": "high",
    "bauix.exe": "high"
  },
  "suspicious_domains": {
    "solara.cc": "high",
    "getsolara.dev": "high",
    "xeno.now": "high",
    "wave.cx": "high",
    "ronix.cc": "high",
    "ronix.gg": "high",
    "velocityexploit.com": "high",
    "winterbypass.com": "high",
    "winter.gg": "high",
    "fishstrap.gg": "high",
    "getfishstrap.com": "high",
    "cryptic.gg": "high",
    "crypticexec.com": "high",
    "trigonevo.com": "high",
    "nezur.cc": "high",
    "hydrogen.lat": "high",
    "argonexec.com": "high",
    "sentinel.gg": "high",
    "moon.sex": "high",
    "layuh.gg": "high",
    "getlayuh.com": "high",
    "getnezur.gg": "high",
    "nord-external.com": "high"
  },
  "suspicious_folder_names": {
    "solara": "high",
    "xeno": "high",
    "wave": "high",
    "velocity executor": "high",
    "ronix": "high",
    "winter bypass": "high",
    "fishstrap": "high",
    "cryptic": "high",
    "trigon evo": "high",
    "hydrogen": "high",
    "nezur": "high",
    "argon executor": "high",
    "layuh": "high",
    "autopsy": "high",
    "nocturnal": "high"
  },
  "script_red_flags": {
    "aimbot": "high",
    "silent aim": "high",
    "esp trace": "high",
    "wallbang": "high",
    "chams": "medium",
    "no clip": "medium",
    "getgc()": "high",
    "hookmetamethod": "medium",
    "loadstring(game:HttpGet": "high",
    "loadstring(game:HttpGetAsync": "high"
  }
}
